model/VERSION
model/__init__.py
model/config.yml
model/pipeline.py
model/predict.py
model/train_pipeline.py
model/config/__init__.py
model/config/core.py
model/datasets/__init__.py
model/datasets/test.csv
model/datasets/train.csv
model/processing/__init__.py
model/processing/data_manager.py
model/processing/features.py
model/processing/validation.py
model/trained_models/__init__.py
model/trained_models/model_output_v0.0.1.pkl
csx_mortgage_default_prediction_model-0.0.1.dist-info/METADATA
csx_mortgage_default_prediction_model-0.0.1.dist-info/WHEEL
csx_mortgage_default_prediction_model-0.0.1.dist-info/top_level.txt
csx_mortgage_default_prediction_model-0.0.1.dist-info/RECORD
