Metadata-Version: 2.1
Name: csx-mortgage-default-prediction-model
Version: 0.0.1
Summary: A mortgage default prediction model package.
Home-page: https://github.com/bloodandpoison/deploy-mortgage-default-prediction-model
Author: Sixian Chen
Author-email: csx405634030@gmail.com
License: BSD-3
Classifier: License :: OSI Approved :: MIT License
Classifier: Programming Language :: Python
Classifier: Programming Language :: Python :: 3
Classifier: Programming Language :: Python :: 3.6
Classifier: Programming Language :: Python :: 3.7
Classifier: Programming Language :: Python :: 3.8
Classifier: Programming Language :: Python :: 3.9
Classifier: Programming Language :: Python :: Implementation :: CPython
Classifier: Programming Language :: Python :: Implementation :: PyPy
Requires-Python: >=3.6.0
Requires-Dist: feature-engine (==1.4.1)
Requires-Dist: joblib (==1.1.0)
Requires-Dist: numpy (==1.23.2)
Requires-Dist: packaging (==21.3)
Requires-Dist: pandas (==1.4.3)
Requires-Dist: patsy (==0.5.2)
Requires-Dist: pydantic (==1.9.2)
Requires-Dist: pyparsing (==3.0.9)
Requires-Dist: python-dateutil (==2.8.2)
Requires-Dist: pytz (==2022.2.1)
Requires-Dist: ruamel.yaml (==0.17.21)
Requires-Dist: ruamel.yaml.clib (==0.2.6)
Requires-Dist: scikit-learn (==1.1.2)
Requires-Dist: scipy (==1.9.0)
Requires-Dist: six (==1.16.0)
Requires-Dist: statsmodels (==0.13.2)
Requires-Dist: strictyaml (==1.6.1)
Requires-Dist: threadpoolctl (==3.1.0)
Requires-Dist: typing-extensions (==4.3.0)
